wicspy/__init__.py
wicspy/py.typed
wicspy/config/__init__.py
wicspy/messaging/__init__.py
wicspy/messaging/bark.py
wicspy/scripts/bark.py
wicspy/scripts/radiation.py
wicspy/security/__init__.py
wicspy/server/__init__.py
wicspy/server/monitor.py
wicspy/server/process.py
wicspy/system/__init__.py
wicspy/web/__init__.py
wicspy/web/scraper.py
wicspy/web/seawater_radiation.py
wicspy-0.1.11.dist-info/METADATA
wicspy-0.1.11.dist-info/WHEEL
wicspy-0.1.11.dist-info/entry_points.txt
wicspy-0.1.11.dist-info/licenses/LICENSE
wicspy-0.1.11.dist-info/RECORD
