Metadata-Version: 2.4
Name: wicspy
Version: 0.1.11
Summary: A comprehensive Python utilities library for various tasks
Author-email: wicsp <wicspa@gmail.com>
License: MIT
License-File: LICENSE
Classifier: Development Status :: 3 - Alpha
Classifier: Intended Audience :: Developers
Classifier: License :: OSI Approved :: MIT License
Classifier: Programming Language :: Python :: 3
Classifier: Programming Language :: Python :: 3.10
Classifier: Programming Language :: Python :: 3.11
Classifier: Programming Language :: Python :: 3.12
Requires-Python: >=3.10
Requires-Dist: loguru>=0.7.3
Requires-Dist: pydantic>=2.0.0
Requires-Dist: python-dotenv>=1.0.0
Requires-Dist: requests>=2.32.3
Provides-Extra: dev
Requires-Dist: black>=23.0.0; extra == 'dev'
Requires-Dist: mypy>=1.0.0; extra == 'dev'
Requires-Dist: pdoc>=15.0.1; extra == 'dev'
Requires-Dist: pre-commit>=3.0.0; extra == 'dev'
Requires-Dist: pytest-cov>=4.0.0; extra == 'dev'
Requires-Dist: pytest>=7.0.0; extra == 'dev'
Requires-Dist: ruff>=0.1.0; extra == 'dev'
Provides-Extra: full
Requires-Dist: beautifulsoup4>=4.13.3; extra == 'full'
Requires-Dist: httpx[socks]>=0.24.0; extra == 'full'
Requires-Dist: rich>=13.0.0; extra == 'full'
Provides-Extra: web
Requires-Dist: beautifulsoup4>=4.13.3; extra == 'web'
Requires-Dist: httpx[socks]>=0.24.0; extra == 'web'
